ansiformat/__init__.py
ansiformat/__version__.py
ansiformat/cli.py
ansiformat/utils/__init__.py
ansiformat/utils/log.py
ansiformat-0.0.1.dev1.dist-info/LICENSE
ansiformat-0.0.1.dev1.dist-info/METADATA
ansiformat-0.0.1.dev1.dist-info/WHEEL
ansiformat-0.0.1.dev1.dist-info/entry_points.txt
ansiformat-0.0.1.dev1.dist-info/top_level.txt
ansiformat-0.0.1.dev1.dist-info/RECORD
